tfwrap/__init__.py
tfwrap/__main__.py
tfwrap/main.py
tfwrap/version.py
tfwrap-1.0.2.dist-info/licenses/LICENSE
tfwrap-1.0.2.dist-info/METADATA
tfwrap-1.0.2.dist-info/WHEEL
tfwrap-1.0.2.dist-info/entry_points.txt
tfwrap-1.0.2.dist-info/top_level.txt
tfwrap-1.0.2.dist-info/RECORD
