Metadata-Version: 2.4
Name: tfwrap
Version: 1.0.2
Summary: A CLI tool for managing Terraform remote backends and bootstrapping infrastructure
License:                     GNU GENERAL PUBLIC LICENSE
Project-URL: Homepage, https://github.com/timothy-cloudopsguy/tfwrap
Project-URL: Repository, https://github.com/timothy-cloudopsguy/tfwrap
Project-URL: Issues, https://github.com/timothy-cloudopsguy/tfwrap/issues
Classifier: Development Status :: 4 - Beta
Classifier: Intended Audience :: Developers
Classifier: Intended Audience :: System Administrators
Classifier: License :: OSI Approved :: GNU General Public License v3 (GPLv3)
Classifier: Operating System :: OS Independent
Classifier: Programming Language :: Python :: 3
Classifier: Programming Language :: Python :: 3.6
Classifier: Programming Language :: Python :: 3.7
Classifier: Programming Language :: Python :: 3.8
Classifier: Programming Language :: Python :: 3.9
Classifier: Programming Language :: Python :: 3.10
Classifier: Programming Language :: Python :: 3.11
Classifier: Programming Language :: Python :: 3.12
Classifier: Topic :: System :: Systems Administration
Classifier: Topic :: Utilities
Requires-Python: >=3.6
License-File: LICENSE
Requires-Dist: boto3>=1.17.0
Dynamic: license-file
